<?xml version="1.0"?>
<?xml-stylesheet href="slides.css" type="text/css"?>
<!DOCTYPE Slide>

<Slide xmlns:html="http://www.w3.org/1999/xhtml" xmlns:xlink="http://www.w3.org/1999/xlink">

  <html:img src="mozilla-banner.gif" width="124" height="58" id="logo" />

  <SlideBody>
    <Heading>
      Embedding APIs
    </Heading>
    <SubHeading>
      Approach
    </SubHeading>

    <List>
      <ListItem>Minimal set of APIs for embedding applications:
        <ListItem2>Should be simple for simple embeddings.</ListItem2>
        <ListItem2>Freezing APIs has a cost.</ListItem2>
      </ListItem>
      <ListItem>Complete enough to implement everything that can
                be done with a typical browser UI.
      </ListItem>
      <ListItem>We haven't focused on APIs for component writers yet.</ListItem>
    </List>

  </SlideBody>

  <Bar>
    <Button xlink:type="simple" xlink:href="slide7.xml">Prev</Button>
    <Button xlink:type="simple" xlink:href="slide9.xml">Next</Button>
  </Bar>

</Slide>
