<?xml version="1.0" encoding="utf-8"?>
<hotels xmlns="">
  <country>
    <name>Denmark</name>
    <city>
      <name>Copenhagen</name>
      <hotel>Little Mermaid Inn</hotel>
      <hotel>Nyhavn Hotel</hotel>
    </city>
    <city>
      <name>Ålborg</name>
      <hotel>Skipper Hotel</hotel>
      <hotel>Smugkroen</hotel>
    </city>
  </country>
  <country>
    <name>France</name>
    <city>
      <name>Paris</name>
      <hotel>L'Hotel de la Tour Eiffel</hotel>
      <hotel>Le Ptit Coin</hotel>
    </city>
  </country>
  <country>
    <name>Germany</name>
    <city>
      <name>Düsseldorf</name>
      <hotel>Schnurbart Imbiss</hotel>
      <hotel>Bremer Hotel</hotel>
    </city>
  </country>
  <country>
    <name>Holland</name>
    <city>
      <name>Amsterdam</name>
      <hotel>The Red Tulip</hotel>
      <hotel>Dam Superior</hotel>
    </city>
    <city>
      <name>Den Haag</name>
      <hotel>DH Superior</hotel>
      <hotel>Canal Suites</hotel>
    </city>
  </country>
</hotels>
